odoo/addons/ssi_decorator/README.rst
odoo/addons/ssi_decorator/__init__.py
odoo/addons/ssi_decorator/__manifest__.py
odoo/addons/ssi_decorator/ssi_decorator.py
odoo/addons/ssi_decorator/models/__init__.py
odoo/addons/ssi_decorator/models/ssi_decorator_mixin.py
odoo/addons/ssi_decorator/static/description/icon.png
odoo14_addon_ssi_decorator-14.0.1.5.1.dist-info/METADATA
odoo14_addon_ssi_decorator-14.0.1.5.1.dist-info/WHEEL
odoo14_addon_ssi_decorator-14.0.1.5.1.dist-info/top_level.txt
odoo14_addon_ssi_decorator-14.0.1.5.1.dist-info/RECORD
